watonapi/__init__.py
watonapi/address.py
watonapi/codec.py
watonapi/connection.py
watonapi/dispatcher.py
watonapi/errors.py
watonapi/packets.py
watonapi/server.py
WatonAPI-0.1.dist-info/LICENSE
WatonAPI-0.1.dist-info/METADATA
WatonAPI-0.1.dist-info/WHEEL
WatonAPI-0.1.dist-info/top_level.txt
WatonAPI-0.1.dist-info/RECORD
