Metadata-Version: 2.1
Name: WatonAPI
Version: 0.1
Summary: Python API for the WatonPlugin
Home-page: https://github.com/Waton-Corp/WatonAPI
Author: DevBPM, lamorisi0n
License: GPL-3.0
Platform: UNKNOWN
Classifier: Operating System :: OS Independent
License-File: LICENSE
Requires-Dist: dnspython (==2.1.0)
